thothdjango/__init__.py
thothdjango/admin.py
thothdjango/models.py
thothlibrary/__init__.py
thothlibrary/auth.py
thothlibrary/cli.py
thothlibrary/client.py
thothlibrary/errors.py
thothlibrary/graphql.py
thothlibrary/mutation.py
thothlibrary/query.py
thothlibrary/thoth-0_4_2/__init__.py
thothlibrary/thoth-0_4_2/endpoints.py
thothlibrary/thoth-0_4_2/structures.py
thothlibrary/thoth-0_4_2/fixtures/QUERIES
thothlibrary/thoth-0_5_0/__init__.py
thothlibrary/thoth-0_5_0/endpoints.py
thothlibrary/thoth-0_5_0/structures.py
thothlibrary/thoth-0_5_0/fixtures/QUERIES
thothlibrary/thoth-0_6_0/__init__.py
thothlibrary/thoth-0_6_0/endpoints.py
thothlibrary/thoth-0_6_0/structures.py
thothlibrary/thoth-0_6_0/fixtures/QUERIES
thothlibrary/thoth-0_8_0/__init__.py
thothlibrary/thoth-0_8_0/endpoints.py
thothlibrary/thoth-0_8_0/structures.py
thothlibrary/thoth-0_8_0/fixtures/QUERIES
thothlibrary/thoth-0_8_4/__init__.py
thothlibrary/thoth-0_8_4/endpoints.py
thothlibrary/thoth-0_8_4/structures.py
thothlibrary/thoth-0_8_4/fixtures/QUERIES
thothlibrary/thoth-0_9_0/__init__.py
thothlibrary/thoth-0_9_0/endpoints.py
thothlibrary/thoth-0_9_0/structures.py
thothlibrary/thoth-0_9_0/fixtures/QUERIES
thothlibrary-0.30.0.dist-info/licenses/LICENSE
thothrest/__init__.py
thothrest/cli.py
thothrest/client.py
thothrest/errors.py
thothrest/thoth-0_4_2/__init__.py
thothrest/thoth-0_4_2/endpoints.py
thothrest/thoth-0_4_2/structures.py
thothlibrary-0.30.0.dist-info/METADATA
thothlibrary-0.30.0.dist-info/WHEEL
thothlibrary-0.30.0.dist-info/top_level.txt
thothlibrary-0.30.0.dist-info/RECORD
