Metadata-Version: 2.4
Name: thothlibrary
Version: 0.30.0
Summary: Python client for Thoth's APIs
Home-page: https://github.com/thoth-pub/thoth-client
Author: Javier Arias, Martin Paul Eve
Author-email: info@thoth.pub
License: Apache 2.0
Platform: any
Classifier: Programming Language :: Python :: 3
Classifier: License :: OSI Approved :: Apache Software License
License-File: LICENSE
Requires-Dist: requests==2.32.3
Requires-Dist: fire==0.6.0
Requires-Dist: munch==3.0.0
Requires-Dist: requests_mock==1.12.1
Requires-Dist: ascii_magic==2.3.0
Requires-Dist: graphqlclient==0.2.4
Dynamic: author
Dynamic: author-email
Dynamic: classifier
Dynamic: description
Dynamic: description-content-type
Dynamic: home-page
Dynamic: license
Dynamic: license-file
Dynamic: platform
Dynamic: requires-dist
Dynamic: summary
